medrical/__init__.py
medrical/cli/__init__.py
medrical/cli/cli.py
medrical/config/__init__.py
medrical/config/config.py
medrical/config/pipeline.cfg
medrical/config/schemas/biometrics.avsc
medrical/config/schemas/key.avsc
medrical/config/ssl/README.md
medrical/producer/__init__.py
medrical/producer/patient.py
medrical/producer/producer.py
medrical-0.1.10.data/data/config/pipeline.cfg
medrical-0.1.10.data/data/schemas/biometrics.avsc
medrical-0.1.10.data/data/schemas/key.avsc
tests/__init__.py
tests/test_connector.py
tests/test_producer.py
medrical-0.1.10.dist-info/LICENSE
medrical-0.1.10.dist-info/METADATA
medrical-0.1.10.dist-info/WHEEL
medrical-0.1.10.dist-info/entry_points.txt
medrical-0.1.10.dist-info/top_level.txt
medrical-0.1.10.dist-info/RECORD
