Metadata-Version: 2.1
Name: medrical
Version: 0.1.10
Summary: Medrical is a real-time medical biometric monitoring system, powered by Apache Kafka and postgreSQL.
Home-page: https://github.com/DimitrisPr/medrical
Author: Dimitris Prasakis
Author-email: dimitris@prasakis.com
License: UNKNOWN
Platform: UNKNOWN
Requires-Dist: CacheControl (==0.12.6)
Requires-Dist: aiven-client (==2.10.0)
Requires-Dist: appdirs (==1.4.3)
Requires-Dist: astroid (==2.4.2)
Requires-Dist: avro-python3 (==1.10.1)
Requires-Dist: certifi (==2019.11.28)
Requires-Dist: chardet (==3.0.4)
Requires-Dist: colorama (==0.4.3)
Requires-Dist: confluent-kafka (==1.6.0)
Requires-Dist: contextlib2 (==0.6.0)
Requires-Dist: distlib (==0.3.0)
Requires-Dist: distro (==1.4.0)
Requires-Dist: fastavro (==1.3.2)
Requires-Dist: html5lib (==1.0.1)
Requires-Dist: idna (==2.8)
Requires-Dist: ipaddr (==2.2.0)
Requires-Dist: isort (==5.7.0)
Requires-Dist: lazy-object-proxy (==1.4.3)
Requires-Dist: lockfile (==0.12.2)
Requires-Dist: mccabe (==0.6.1)
Requires-Dist: msgpack (==0.6.2)
Requires-Dist: packaging (==20.3)
Requires-Dist: pep517 (==0.8.2)
Requires-Dist: progress (==1.5)
Requires-Dist: psycopg2-binary
Requires-Dist: pycodestyle (==2.6.0)
Requires-Dist: pylint (==2.6.0)
Requires-Dist: pyparsing (==2.4.6)
Requires-Dist: pytoml (==0.1.21)
Requires-Dist: requests (==2.22.0)
Requires-Dist: retrying (==1.3.3)
Requires-Dist: six (==1.14.0)
Requires-Dist: toml (==0.10.2)
Requires-Dist: urllib3 (==1.25.8)
Requires-Dist: webencodings (==0.5.1)
Requires-Dist: wrapt (==1.12.1)
